freestylo/AlliterationAnnotation.py
freestylo/ChiasmusAnnotation.py
freestylo/Configs.py
freestylo/EpiphoraAnnotation.py
freestylo/MGHPreprocessor.py
freestylo/MetaphorAnnotation.py
freestylo/PolysyndetonAnnotation.py
freestylo/SimilarityNN.py
freestylo/TextObject.py
freestylo/TextPreprocessor.py
freestylo/__init__.py
freestylo/__main__.py
freestylo/freestylo_main.py
freestylo-0.8.8.dist-info/licenses/LICENSE
freestylo-0.8.8.dist-info/METADATA
freestylo-0.8.8.dist-info/WHEEL
freestylo-0.8.8.dist-info/entry_points.txt
freestylo-0.8.8.dist-info/top_level.txt
freestylo-0.8.8.dist-info/RECORD
