Metadata-Version: 2.4
Name: freestylo
Version: 0.8.8
Summary: A tool for stylistic device detection."
Home-page: https://github.com/cvjena/freestylo
Author: Felix Schneider
Author-email: felix.schneider@uni-jena.de
License: GNU General Public License v3.0
Project-URL: Source, https://github.com/cvjena/freestylo
Project-URL: Tracker, https://github.com/cvjena/freestylo/issues
Platform: any
Classifier: Development Status :: 4 - Beta
Classifier: Intended Audience :: Developers
Requires-Python: >=3.12
License-File: LICENSE
Requires-Dist: setuptools>=75.0
Requires-Dist: torch
Requires-Dist: spacy==3.8.2
Requires-Dist: numpy
Requires-Dist: pytest
Requires-Dist: scikit-learn
Requires-Dist: scipy
Requires-Dist: cltk<1.0
Requires-Dist: wget
Requires-Dist: fasttext
Provides-Extra: testing
Requires-Dist: setuptools>=75.0; extra == "testing"
Requires-Dist: pytest; extra == "testing"
Requires-Dist: pytest-cov; extra == "testing"
Dynamic: license-file
